mongoext/__init__.py
mongoext/abc.py
mongoext/collection.py
mongoext/cursor.py
mongoext/document.py
mongoext/exc.py
mongoext/schema.py
mongoext-0.4.0.dist-info/DESCRIPTION.rst
mongoext-0.4.0.dist-info/METADATA
mongoext-0.4.0.dist-info/metadata.json
mongoext-0.4.0.dist-info/RECORD
mongoext-0.4.0.dist-info/top_level.txt
mongoext-0.4.0.dist-info/WHEEL
